mux/mux.v
module mux4to1 (
    input  wire [3:0] I,
    input  wire [1:0] S,
    output reg Y
);

always @(*) begin
    case (S)
        2'b00: Y = I[0];
        2'b01: Y = I[1];
        2'b10: Y = I[2];
        2'b11: Y = I[3];
        default: Y = 1'b0;
    endcase
end

endmodule

mux/mux_tb.v
`timescale 1ns/1ps

module mux4to1_tb;

reg [3:0] I;
reg [1:0] S;
wire Y;

mux4to1 uut (
    .I(I),
    .S(S),
    .Y(Y)
);

initial begin
    $dumpfile("mux.vcd");
    $dumpvars(0, mux4to1_tb);

    $display("Time\tI\tS\tY");
    $display("------------------------");

    I = 4'b1010;

    S = 2'b00;
    #10;
    $display("%0t\t%b\t%b\t%b", $time, I, S, Y);

    S = 2'b01;
    #10;
    $display("%0t\t%b\t%b\t%b", $time, I, S, Y);

    S = 2'b10;
    #10;
    $display("%0t\t%b\t%b\t%b", $time, I, S, Y);

    S = 2'b11;
    #10;
    $display("%0t\t%b\t%b\t%b", $time, I, S, Y);

    I = 4'b0101;

    S = 2'b00;
    #10;
    $display("%0t\t%b\t%b\t%b", $time, I, S, Y);

    S = 2'b01;
    #10;
    $display("%0t\t%b\t%b\t%b", $time, I, S, Y);

    S = 2'b10;
    #10;
    $display("%0t\t%b\t%b\t%b", $time, I, S, Y);

    S = 2'b11;
    #10;
    $display("%0t\t%b\t%b", $time, I, S, Y);

    $finish;
end

endmodule

mux/mux.vcd
$date
	Thu Aug 20 09:44:09 2026
$end
$version
	Icarus Verilog
$end
$timescale
	1ps
$end
$scope module mux4to1_tb $end
$var wire 1 ! Y $end
$var reg 4 " I [3:0] $end
$var reg 2 # S [1:0] $end
$scope module uut $end
$var wire 4 $ I [3:0] $end
$var wire 2 % S [1:0] $end
$var reg 1 ! Y $end
$upscope $end
$upscope $end
$enddefinitions $end
#0
$dumpvars
b0 %
b1010 $
b0 #
b1010 "
0!
$end
#10000
1!
b1 #
b1 %
#20000
0!
b10 #
b10 %
#30000
1!
b11 #
b11 %
#40000
b0 #
b0 %
b101 "
b101 $
#50000
0!
b1 #
b1 %
#60000
1!
b10 #
b10 %
#70000
0!
b11 #
b11 %
